README.md
setup.cfg
setup.py
cunlp/__init__.py
cunlp/_embedding
cunlp/_model_pos
cunlp/_model_pos_map
cunlp/_model_tokenizer
cunlp/embedding.py
cunlp/model.py
cunlp.egg-info/PKG-INFO
cunlp.egg-info/SOURCES.txt
cunlp.egg-info/dependency_links.txt
cunlp.egg-info/requires.txt
cunlp.egg-info/top_level.txt