Metadata-Version: 1.1
Name: cunlp
Version: 0.3.2
Summary: Chulalongkorn University Natural Languages Processing Library (Beta)
Home-page: https://github.com/jrkns/cunlp
Author: Danupat Khamnuansin, Nuttasit Mahakusolsirikul
Author-email: danupat.K@student.chula.ac.th, nuttasit.M@student.chula.ac.th
License: UNKNOWN
Download-URL: https://github.com/jrkns/cunlp/dist/0.3.2.tar.gz
Keywords: nlp,thai
Platform: UNKNOWN
